tketool/JConfig.py
tketool/ServiceShelve.py
tketool/__init__.py
tketool/cmd_utils.py
tketool/files.py
tketool/hash_util.py
tketool/lmc_console_tool.py
tketool/logs.py
tketool/sample_console_tool.py
tketool/setup.py
tketool/buffer/__init__.py
tketool/buffer/bufferbase.py
tketool/buffer/local_many.py
tketool/buffer/local_one.py
tketool/buffer/local_onesqlite.py
tketool/buffer/redis.py
tketool/evaluate/EvalutionBase.py
tketool/evaluate/__init__.py
tketool/evaluate/scores.py
tketool/lmc/__init__.py
tketool/lmc/additional_output_parser.py
tketool/lmc/embeddings.py
tketool/lmc/llms.py
tketool/lmc/lmc_linked.py
tketool/lmc/models.py
tketool/lmc/prompt_utils.py
tketool/lmc/prompts/__init__.py
tketool/lmc/prompts/prompt_controller.py
tketool/lmc/prompts/templates/chinese/codereviews.txt
tketool/lmc/prompts/templates/chinese/comments_level1.txt
tketool/lmc/prompts/templates/english/codereviews.txt
tketool/lmc/prompts/templates/english/comments_level1.txt
tketool/lmc/tasks/__init__.py
tketool/lmc/tasks/code_comment.py
tketool/lmc/tasks/code_review.py
tketool/lmc/tasks/task_init.py
tketool/lmc/tasks/translate.py
tketool/markdowns/__init__.py
tketool/markdowns/markdown.py
tketool/ml/HMM.py
tketool/ml/__init__.py
tketool/ml/graph.py
tketool/ml/mapping.py
tketool/ml/modelbase.py
tketool/ml/string_match.py
tketool/mlsample/LocalSampleSource.py
tketool/mlsample/MemorySampleSource.py
tketool/mlsample/MinioSampleSource.py
tketool/mlsample/NLSampleSource.py
tketool/mlsample/RandomSet.py
tketool/mlsample/SSHSampleSource.py
tketool/mlsample/SampleSet.py
tketool/mlsample/SampleSet_Util.py
tketool/mlsample/__init__.py
tketool/mlsample/converts.py
tketool/pyml/__init__.py
tketool/pyml/pytrainer.py
tketool/pyml/pytrainer_accelerate.py
tketool/pyml/pytrainer_deepspeed.py
tketool/pyml/trainbase.py
tketool/pyml/utils.py
tketool/pyml/trainerplugins/__init__.py
tketool/pyml/trainerplugins/dashboard.py
tketool/pyml/trainerplugins/evaluate_trainset.py
tketool/pyml/trainerplugins/grad_log.py
tketool-0.7.47.dist-info/METADATA
tketool-0.7.47.dist-info/WHEEL
tketool-0.7.47.dist-info/entry_points.txt
tketool-0.7.47.dist-info/top_level.txt
tketool-0.7.47.dist-info/RECORD
