Metadata-Version: 2.1
Name: tketool
Version: 0.7.47
Summary: Some base methods for developing
Home-page: http://www.example.com/~cschultz/bvote/
Author: Ke
Author-email: jiangke1207@icloud.com
Classifier: Programming Language :: Python :: 3
Classifier: License :: OSI Approved :: MIT License
Classifier: Operating System :: OS Independent
Requires-Dist: numpy
Provides-Extra: all
Requires-Dist: hmmlearn (==0.3.0) ; extra == 'all'
Requires-Dist: pypdf2 (==3.0.1) ; extra == 'all'
Requires-Dist: paramiko (==2.12.0) ; extra == 'all'
Requires-Dist: minio (==7.1.11) ; extra == 'all'
Requires-Dist: redis (==4.5.4) ; extra == 'all'
Requires-Dist: torch (==2.0.1) ; extra == 'all'
Requires-Dist: flask (==2.1.1) ; extra == 'all'
Requires-Dist: flask-restful ; extra == 'all'
Requires-Dist: langchain (==0.1.0) ; extra == 'all'
Requires-Dist: openai (==1.7.1) ; extra == 'all'
Requires-Dist: prettytable ; extra == 'all'
Requires-Dist: socksio ; extra == 'all'
Provides-Extra: llm_train
Requires-Dist: accelerate ; extra == 'llm_train'
Requires-Dist: deepspeed ; extra == 'llm_train'
Provides-Extra: lmc
Requires-Dist: langchain (==0.1.0) ; extra == 'lmc'
Requires-Dist: openai (==1.7.1) ; extra == 'lmc'
Requires-Dist: httpx ; extra == 'lmc'
Provides-Extra: ml
Requires-Dist: hmmlearn (==0.3.0) ; extra == 'ml'
Provides-Extra: sample_set
Requires-Dist: pypdf2 (==3.0.1) ; extra == 'sample_set'
Requires-Dist: paramiko (==2.12.0) ; extra == 'sample_set'
Requires-Dist: minio (==7.1.11) ; extra == 'sample_set'
Requires-Dist: redis (==4.5.4) ; extra == 'sample_set'
Requires-Dist: prettytable ; extra == 'sample_set'
Provides-Extra: torch_dep
Requires-Dist: torch (==2.0.1) ; extra == 'torch_dep'
Requires-Dist: flask (==2.1.1) ; extra == 'torch_dep'
Requires-Dist: flask-restful ; extra == 'torch_dep'
